oxymouse/__init__.py
oxymouse/algorithms/__init__.py
oxymouse/algorithms/base.py
oxymouse/algorithms/bezier_mouse/__init__.py
oxymouse/algorithms/bezier_mouse/bezier_mouse.py
oxymouse/algorithms/gaussian_mouse/__init__.py
oxymouse/algorithms/gaussian_mouse/gaussian_mouse.py
oxymouse/algorithms/perlin_mouse/__init__.py
oxymouse/algorithms/perlin_mouse/perlin_mouse.py
oxymouse/oxymouse.py
oxymouse-1.1.0.dist-info/LICENSE
oxymouse-1.1.0.dist-info/METADATA
oxymouse-1.1.0.dist-info/WHEEL
oxymouse-1.1.0.dist-info/RECORD
