Metadata-Version: 2.1
Name: oxymouse
Version: 1.1.0
Summary: 
Author: Tadas Gedgaudas
Author-email: tadas.gedgaudas@oxylabs.io
Requires-Python: >=3.10,<4.0
Classifier: Programming Language :: Python :: 3
Classifier: Programming Language :: Python :: 3.10
Classifier: Programming Language :: Python :: 3.11
Classifier: Programming Language :: Python :: 3.12
Requires-Dist: matplotlib (>=3.9.2,<3.10.0)
Requires-Dist: noise (>=1.2.2,<1.3.0)
Requires-Dist: pyhm (>=0.0.7,<0.1.0)
Requires-Dist: typer (>=0.12.5,<0.13.0)
